ltts/__init__.py
ltts/backends.py
ltts/cli.py
ltts/kokoro_backend.py
ltts/qwen_backend.py
ltts-0.4.2.dist-info/licenses/LICENSE
ltts-0.4.2.dist-info/METADATA
ltts-0.4.2.dist-info/WHEEL
ltts-0.4.2.dist-info/entry_points.txt
ltts-0.4.2.dist-info/top_level.txt
ltts-0.4.2.dist-info/RECORD
