Metadata-Version: 2.4
Name: ltts
Version: 0.4.2
Summary: Text-to-speech CLI using Qwen3-TTS or Kokoro TTS
Author: Frank Chiarulli Jr.
License-Expression: MIT
Project-URL: Repository, https://github.com/fcjr/ltts
Project-URL: Issues, https://github.com/fcjr/ltts/issues
Classifier: Programming Language :: Python :: 3
Classifier: Programming Language :: Python :: 3 :: Only
Classifier: Programming Language :: Python :: 3.12
Classifier: Programming Language :: Python :: 3.13
Requires-Python: >=3.12
License-File: LICENSE
Requires-Dist: soundfile>=0.13.1
Requires-Dist: sounddevice>=0.4.6
Requires-Dist: qwen-tts>=0.0.5
Requires-Dist: kokoro>=0.9.4
Requires-Dist: misaki[ja,zh]>=0.9.4
Requires-Dist: spacy>=3.8.0
Requires-Dist: unidic>=1.1.0
Requires-Dist: numba>=0.59.0
Provides-Extra: cuda
Requires-Dist: flash-attn>=2.0.0; extra == "cuda"
Dynamic: license-file
